protein_distribution/__init__.py
protein_distribution/console.py
protein_distribution/correlation_analysis.py
protein_distribution/dataio.py
protein_distribution/log.py
protein_distribution/protein_info.py
protein_distribution/py.typed
protein_distribution/run_all.py
protein_distribution/significance_testing.py
protein_distribution/tables.py
protein_distribution/uniprot.py
protein_distribution/visualization.py
protein_distribution/resources/data.xlsx
protein_distribution/resources/data_merged.xlsx
protein_distribution/resources/data_normalization.xlsx
protein_distribution/resources/data_raw.xlsx
protein_distribution/resources/sid2category.json
protein_distribution/resources/uniprot.json
protein_distribution/resources/uniprot2sid.json
protein_distribution/studies/__init__.py
protein_distribution/studies/vildhede2015.py
protein_distribution/studies/wegler2022.py
protein_distribution-0.1.9.dist-info/LICENSE
protein_distribution-0.1.9.dist-info/METADATA
protein_distribution-0.1.9.dist-info/WHEEL
protein_distribution-0.1.9.dist-info/top_level.txt
protein_distribution-0.1.9.dist-info/zip-safe
protein_distribution-0.1.9.dist-info/RECORD
