Metadata-Version: 2.2
Name: protein-distribution
Version: 0.1.9
Summary: pyton package for accessing protein distribution data.
Home-page: https://github.com/matthiaskoenig/protein-distribution
Download-URL: https://pypi.org/project/protein-distribution
Author: Matthias Koenig
Author-email: konigmatt@googlemail.com
Maintainer: Matthias Koenig
Maintainer-email: konigmatt@googlemail.com
License: LGPL-3.0
Project-URL: Source Code, https://github.com/matthiaskoenig/protein-distribution
Project-URL: Documentation, https://github.com/matthiaskoenig/protein-distribution
Project-URL: Bug Tracker, https://github.com/matthiaskoenig/protein-distribution/issues
Keywords: liver,CYP,UGT,SLC,ABC
Classifier: Development Status :: 4 - Beta
Classifier: Intended Audience :: Science/Research
Classifier: License :: OSI Approved :: GNU Lesser General Public License v3 (LGPLv3)
Classifier: Operating System :: OS Independent
Classifier: Programming Language :: Python :: 3.12
Classifier: Programming Language :: Python :: 3.13
Classifier: Programming Language :: Python :: Implementation :: CPython
Classifier: Topic :: Scientific/Engineering
Classifier: Topic :: Scientific/Engineering :: Bio-Informatics
Requires-Python: >=3.12
License-File: LICENSE
Requires-Dist: requests>=2.32.3
Requires-Dist: pandas>=2.2.3
Requires-Dist: numpy>=2.2.2
Requires-Dist: scipy>=1.15.1
Requires-Dist: matplotlib>=3.10.0
Requires-Dist: seaborn>=0.13.2
Requires-Dist: openpyxl>=3.1.5
Requires-Dist: rich>=13.9.4
Requires-Dist: xmltodict>=0.14.2
Requires-Dist: pydantic>=2.10.6
Requires-Dist: statsmodels>=0.14.4
Provides-Extra: development
Requires-Dist: pip-tools>6.5.1; extra == "development"
Requires-Dist: black>=25.1.0; extra == "development"
Requires-Dist: bump2version>=1.0.1; extra == "development"
Requires-Dist: isort>=5.12.0; extra == "development"
Requires-Dist: tox>=4.11.1; extra == "development"
Requires-Dist: flake8>=4.0.1; extra == "development"
Requires-Dist: flake8-mypy>=17.8.0; extra == "development"
Requires-Dist: mypy>=0.931; extra == "development"
Requires-Dist: pytest>=7.0.1; extra == "development"
Requires-Dist: pytest-cov>=3.0.0; extra == "development"
Dynamic: download-url
